little_cheesemonger/__init__.py
little_cheesemonger/_cli.py
little_cheesemonger/_constants.py
little_cheesemonger/_errors.py
little_cheesemonger/_loader.py
little_cheesemonger/_platform.py
little_cheesemonger/_run.py
little_cheesemonger/_types.py
little_cheesemonger/py.typed
tests/__init__.py
tests/constants.py
tests/integration/__init__.py
tests/integration/test_custom_loader.py
tests/integration/test_default_loader.py
tests/integration/assets/__init__.py
tests/integration/assets/custom_loader.py
tests/unit/__init__.py
tests/unit/test_cli.py
tests/unit/test_loader.py
tests/unit/test_platform.py
tests/unit/test_run.py
little_cheesemonger-0.2.1.dist-info/LICENSE
little_cheesemonger-0.2.1.dist-info/METADATA
little_cheesemonger-0.2.1.dist-info/WHEEL
little_cheesemonger-0.2.1.dist-info/entry_points.txt
little_cheesemonger-0.2.1.dist-info/top_level.txt
little_cheesemonger-0.2.1.dist-info/RECORD
